slash/__init__.py
slash/__version__.py
slash/app.py
slash/assertions.py
slash/cleanups.py
slash/conf.py
slash/ctx.py
slash/exception_handling.py
slash/exceptions.py
slash/exthook.py
slash/hooks.py
slash/interfaces.py
slash/loader.py
slash/log.py
slash/resuming.py
slash/runner.py
slash/site.py
slash/warnings.py
slash/core/__init__.py
slash/core/cleanup_manager.py
slash/core/details.py
slash/core/error.py
slash/core/exclusions.py
slash/core/function_test.py
slash/core/local_config.py
slash/core/markers.py
slash/core/metadata.py
slash/core/requirements.py
slash/core/result.py
slash/core/runnable_test.py
slash/core/runnable_test_factory.py
slash/core/scope_manager.py
slash/core/session.py
slash/core/tagging.py
slash/core/test.py
slash/core/variation.py
slash/core/variation_factory.py
slash/core/fixtures/__init__.py
slash/core/fixtures/active_fixture.py
slash/core/fixtures/fixture.py
slash/core/fixtures/fixture_base.py
slash/core/fixtures/fixture_store.py
slash/core/fixtures/namespace.py
slash/core/fixtures/parameters.py
slash/core/fixtures/utils.py
slash/ext/__init__.py
slash/frontend/__init__.py
slash/frontend/list_config.py
slash/frontend/main.py
slash/frontend/slash_list.py
slash/frontend/slash_list_plugins.py
slash/frontend/slash_run.py
slash/parallel/__init__.py
slash/parallel/parallel_manager.py
slash/parallel/server.py
slash/parallel/tests_distributer.py
slash/parallel/worker.py
slash/parallel/worker_configuration.py
slash/plugins/__init__.py
slash/plugins/interface.py
slash/plugins/plugin_manager.py
slash/plugins/registration_info.py
slash/plugins/builtin/__init__.py
slash/plugins/builtin/ci_links.py
slash/plugins/builtin/coverage.py
slash/plugins/builtin/email_template.j2
slash/plugins/builtin/notifications.py
slash/plugins/builtin/signal_handling.py
slash/plugins/builtin/xunit.py
slash/reporting/__init__.py
slash/reporting/console_reporter.py
slash/reporting/null_reporter.py
slash/reporting/reporter_interface.py
slash/utils/__init__.py
slash-1.15.0.dist-info/METADATA
slash-1.15.0.dist-info/WHEEL
slash-1.15.0.dist-info/entry_points.txt
slash-1.15.0.dist-info/licenses/LICENSE
slash-1.15.0.dist-info/RECORD
